<annotation>
	<folder>JPEGImages</folder>
	<filename>224.png</filename>
	<path>E:\Programming\AI\withMaskDataset\new_dataset\train\VOCdevkit\VOC2021\JPEGImages\224.png</path>
	<source>
		<database>Unknown</database>
	</source>
	<size>
		<width>400</width>
		<height>267</height>
		<depth>3</depth>
	</size>
	<segmented>0</segmented>
	<object>
		<name>with_mask_good</name>
		<pose>Unspecified</pose>
		<truncated>0</truncated>
		<difficult>0</difficult>
		<bndbox>
			<xmin>273</xmin>
			<ymin>102</ymin>
			<xmax>330</xmax>
			<ymax>162</ymax>
		</bndbox>
	</object>
	<object>
		<name>with_mask_good</name>
		<pose>Unspecified</pose>
		<truncated>0</truncated>
		<difficult>0</difficult>
		<bndbox>
			<xmin>117</xmin>
			<ymin>95</ymin>
			<xmax>186</xmax>
			<ymax>170</ymax>
		</bndbox>
	</object>
</annotation>
