<annotation>
	<folder>305data</folder>
	<filename>357.png</filename>
	<path>E:\Programming\AI\DataSets\withMaskDataset\305data\357.png</path>
	<source>
		<database>Unknown</database>
	</source>
	<size>
		<width>500</width>
		<height>500</height>
		<depth>3</depth>
	</size>
	<segmented>0</segmented>
	<object>
		<name>with_mask_good</name>
		<pose>Unspecified</pose>
		<truncated>0</truncated>
		<difficult>0</difficult>
		<bndbox>
			<xmin>85</xmin>
			<ymin>24</ymin>
			<xmax>447</xmax>
			<ymax>377</ymax>
		</bndbox>
	</object>
</annotation>
