<annotation>
	<folder>305data</folder>
	<filename>369.png</filename>
	<path>E:\Programming\AI\DataSets\withMaskDataset\305data\369.png</path>
	<source>
		<database>Unknown</database>
	</source>
	<size>
		<width>400</width>
		<height>267</height>
		<depth>3</depth>
	</size>
	<segmented>0</segmented>
	<object>
		<name>no_mask</name>
		<pose>Unspecified</pose>
		<truncated>0</truncated>
		<difficult>0</difficult>
		<bndbox>
			<xmin>13</xmin>
			<ymin>105</ymin>
			<xmax>47</xmax>
			<ymax>133</ymax>
		</bndbox>
	</object>
	<object>
		<name>with_mask_good</name>
		<pose>Unspecified</pose>
		<truncated>0</truncated>
		<difficult>0</difficult>
		<bndbox>
			<xmin>98</xmin>
			<ymin>78</ymin>
			<xmax>149</xmax>
			<ymax>144</ymax>
		</bndbox>
	</object>
	<object>
		<name>with_mask_good</name>
		<pose>Unspecified</pose>
		<truncated>0</truncated>
		<difficult>0</difficult>
		<bndbox>
			<xmin>145</xmin>
			<ymin>108</ymin>
			<xmax>183</xmax>
			<ymax>156</ymax>
		</bndbox>
	</object>
</annotation>
