<annotation>
	<folder>305data</folder>
	<filename>496.png</filename>
	<path>E:\Programming\AI\DataSets\withMaskDataset\305data\496.png</path>
	<source>
		<database>Unknown</database>
	</source>
	<size>
		<width>400</width>
		<height>312</height>
		<depth>3</depth>
	</size>
	<segmented>0</segmented>
	<object>
		<name>with_mask_good</name>
		<pose>Unspecified</pose>
		<truncated>0</truncated>
		<difficult>0</difficult>
		<bndbox>
			<xmin>204</xmin>
			<ymin>14</ymin>
			<xmax>255</xmax>
			<ymax>59</ymax>
		</bndbox>
	</object>
	<object>
		<name>with_mask_good</name>
		<pose>Unspecified</pose>
		<truncated>0</truncated>
		<difficult>0</difficult>
		<bndbox>
			<xmin>67</xmin>
			<ymin>145</ymin>
			<xmax>111</xmax>
			<ymax>176</ymax>
		</bndbox>
	</object>
</annotation>
